abgrouponline/__init__.py
abgrouponline/core/__init__.py
abgrouponline/core/base_model.py
abgrouponline/core/config.py
abgrouponline/core/model_loader.py
abgrouponline/core/model_manager.py
abgrouponline/core/registry.py
abgrouponline/healthcare/__init__.py
abgrouponline/healthcare/diabetes_classifier.py
abgrouponline/utils/__init__.py
abgrouponline/utils/compatibility.py
abgrouponline/utils/config.py
abgrouponline/utils/logging_utils.py
abgrouponline-1.0.4.dist-info/LICENSE
abgrouponline-1.0.4.dist-info/METADATA
abgrouponline-1.0.4.dist-info/WHEEL
abgrouponline-1.0.4.dist-info/entry_points.txt
abgrouponline-1.0.4.dist-info/top_level.txt
abgrouponline-1.0.4.dist-info/RECORD
