Metadata-Version: 2.1
Name: abgrouponline
Version: 1.0.4
Summary: State-of-the-art machine learning models and frameworks for real-world applications - Compatible with all Python versions
Home-page: https://github.com/abgrouponline/abgrouponline
Author: ABGroup Research Team
Author-email: research@abgrouponline.com
Project-URL: Bug Reports, https://github.com/abgrouponline/abgrouponline/issues
Project-URL: Source, https://github.com/abgrouponline/abgrouponline
Project-URL: Documentation, https://abgrouponline.readthedocs.io/
Project-URL: Changelog, https://github.com/abgrouponline/abgrouponline/releases
Keywords: machine learning,artificial intelligence,diabetes prediction,medical AI,healthcare,research,python compatibility
Classifier: Development Status :: 4 - Beta
Classifier: Intended Audience :: Developers
Classifier: Intended Audience :: Science/Research
Classifier: License :: OSI Approved :: MIT License
Classifier: Operating System :: OS Independent
Classifier: Programming Language :: Python :: 3
Classifier: Programming Language :: Python :: 3.8
Classifier: Programming Language :: Python :: 3.9
Classifier: Programming Language :: Python :: 3.10
Classifier: Programming Language :: Python :: 3.11
Classifier: Programming Language :: Python :: 3.12
Classifier: Programming Language :: Python :: 3.13
Classifier: Topic :: Scientific/Engineering :: Artificial Intelligence
Classifier: Topic :: Software Development :: Libraries :: Python Modules
Requires-Python: >=3.8
License-File: LICENSE
Requires-Dist: torch >=1.12.0
Requires-Dist: torchvision >=0.13.0
Requires-Dist: scikit-learn >=1.1.0
Requires-Dist: pandas >=1.4.0
Requires-Dist: numpy >=1.21.0
Requires-Dist: matplotlib >=3.5.0
Requires-Dist: seaborn >=0.11.0
Requires-Dist: plotly >=5.10.0
Requires-Dist: requests >=2.28.0
Requires-Dist: tqdm >=4.64.0
Requires-Dist: pyyaml >=6.0
Requires-Dist: xgboost >=1.6.0
Requires-Dist: lightgbm >=3.3.0
Requires-Dist: catboost >=1.0.0
Requires-Dist: imbalanced-learn >=0.9.0
Requires-Dist: pillow >=9.0.0
Requires-Dist: opencv-python >=4.5.0
Requires-Dist: scipy >=1.8.0
Requires-Dist: statsmodels >=0.13.0
Requires-Dist: optuna >=3.0.0
Requires-Dist: hyperopt >=0.2.7
Requires-Dist: shap >=0.40.0
Requires-Dist: lime >=0.2.0
Requires-Dist: tensorflow >=2.9.0 ; python_version < "3.13"
Requires-Dist: keras >=2.9.0 ; python_version < "3.13"
Provides-Extra: dev
Requires-Dist: pytest >=7.0.0 ; extra == 'dev'
Requires-Dist: pytest-cov >=3.0.0 ; extra == 'dev'
Requires-Dist: black >=22.0.0 ; extra == 'dev'
Requires-Dist: flake8 >=4.0.0 ; extra == 'dev'
Requires-Dist: mypy >=0.950 ; extra == 'dev'
Requires-Dist: pre-commit >=2.20.0 ; extra == 'dev'
Provides-Extra: docs
Requires-Dist: sphinx >=5.0.0 ; extra == 'docs'
Requires-Dist: sphinx-rtd-theme >=1.0.0 ; extra == 'docs'
Requires-Dist: sphinx-autodoc-typehints >=1.19.0 ; extra == 'docs'
Provides-Extra: full
Requires-Dist: transformers >=4.20.0 ; extra == 'full'
Requires-Dist: diffusers >=0.20.0 ; extra == 'full'
Requires-Dist: huggingface-hub >=0.15.0 ; extra == 'full'
Requires-Dist: accelerate >=0.20.0 ; extra == 'full'
Requires-Dist: datasets >=2.12.0 ; extra == 'full'
Requires-Dist: evaluate >=0.4.0 ; extra == 'full'
Requires-Dist: wandb >=0.15.0 ; extra == 'full'
Requires-Dist: joblib >=1.1.0 ; extra == 'full'
Requires-Dist: rich >=12.0.0 ; extra == 'full'
Requires-Dist: albumentations >=1.2.0 ; extra == 'full'
Requires-Dist: timm >=0.9.0 ; extra == 'full'
Requires-Dist: einops >=0.6.0 ; extra == 'full'
Requires-Dist: tensorflow >=2.9.0 ; (python_version < "3.13") and extra == 'full'
Requires-Dist: keras >=2.9.0 ; (python_version < "3.13") and extra == 'full'
Requires-Dist: tensorflow-addons >=0.17.0 ; (python_version < "3.13") and extra == 'full'
Provides-Extra: minimal
Requires-Dist: scikit-learn >=1.1.0 ; extra == 'minimal'
Requires-Dist: pandas >=1.4.0 ; extra == 'minimal'
Requires-Dist: numpy >=1.21.0 ; extra == 'minimal'
Requires-Dist: matplotlib >=3.5.0 ; extra == 'minimal'
Provides-Extra: tensorflow
Requires-Dist: tensorflow >=2.9.0 ; (python_version < "3.13") and extra == 'tensorflow'
Requires-Dist: keras >=2.9.0 ; (python_version < "3.13") and extra == 'tensorflow'
Requires-Dist: tensorflow-addons >=0.17.0 ; (python_version < "3.13") and extra == 'tensorflow'
Provides-Extra: transformers
Requires-Dist: transformers >=4.20.0 ; extra == 'transformers'
Requires-Dist: diffusers >=0.20.0 ; extra == 'transformers'
Requires-Dist: huggingface-hub >=0.15.0 ; extra == 'transformers'
